hibpwned/__init__.py
hibpwned/__init__.pyi
hibpwned/py.typed
hibpwned-1.3.9.dist-info/LICENSE
hibpwned-1.3.9.dist-info/METADATA
hibpwned-1.3.9.dist-info/WHEEL
hibpwned-1.3.9.dist-info/top_level.txt
hibpwned-1.3.9.dist-info/RECORD
