Metadata-Version: 2.1
Name: hibpwned
Version: 1.3.9
Summary: A human friendly Python API wrapper for haveibeenpwned.com
Author-email: plasticuproject <plasticuproject@pm.me>
Project-URL: Homepage, https://github.com/plasticuproject/hibpwned
Keywords: hibp,haveibeenpwned,api,wrapper
Classifier: Programming Language :: Python :: 3
Classifier: Development Status :: 5 - Production/Stable
Classifier: Intended Audience :: Developers
Classifier: License :: OSI Approved :: GNU Lesser General Public License v3 (LGPLv3)
Classifier: Operating System :: OS Independent
Classifier: Topic :: Utilities
Classifier: Topic :: Utilities
Requires-Python: >=3.11
License-File: LICENSE
Requires-Dist: requests>=2.32.3
